LICENSE.txt
README.md
setup.cfg
setup.py
lineenhancer/__init__.py
lineenhancer/image_reader.py
lineenhancer/line_enhancer.py
lineenhancer/line_enhancer_test.py
lineenhancer/maskstackcreator.py
lineenhancer.egg-info/PKG-INFO
lineenhancer.egg-info/SOURCES.txt
lineenhancer.egg-info/dependency_links.txt
lineenhancer.egg-info/entry_points.txt
lineenhancer.egg-info/requires.txt
lineenhancer.egg-info/top_level.txt