Metadata-Version: 2.1
Name: lineenhancer
Version: 1.0.9
Summary: Enhancing line images
Home-page: https://github.com/MPI-Dortmund/LineEnhancer
Download-URL: https://github.com/MPI-Dortmund/LineEnhancer/releases/download/1.0.3/lineenhancer-1.0.3.tar.gz
Author: Thorsten Wagner
Author-email: thorsten.wagner@mpi-dortmund.mpg.de
License: MIT
License-File: LICENSE.txt
